parse_smsdb/__init__.py
parse_smsdb/__main__.py
parse_smsdb/parse_smsdb.py
parse_smsdb-0.1.14.dist-info/METADATA
parse_smsdb-0.1.14.dist-info/WHEEL
parse_smsdb-0.1.14.dist-info/entry_points.txt
parse_smsdb-0.1.14.dist-info/licenses/LICENSE
parse_smsdb-0.1.14.dist-info/RECORD
