Metadata-Version: 2.4
Name: parse-smsdb
Version: 0.1.14
Summary: Extracts iMessage, RCS, SMS/MMS chat history from iOS database file.
Project-URL: Homepage, https://github.com/h4x0r/parse_sms.db
Project-URL: Bug Tracker, https://github.com/h4x0r/parse_sms.db/issues
Author-email: Albert Hui <albert@securityronin.com>
License: MIT License
License-File: LICENSE
Classifier: License :: OSI Approved :: MIT License
Classifier: Programming Language :: Python :: 3
Requires-Python: >=3.10
Requires-Dist: pytypedstream
Requires-Dist: typer
